{
  "classes": [
    {
      "id": "warrior",
      "name": "Воин",
      "description": "Закалённый в боях боец ближнего боя. Надёжен и силён.",
      "icon": "🛡️",
      "startingArmy": [
        { "id": "knight", "count": 1 },
        { "id": "archer", "count": 2 }
      ]
    },
    {
      "id": "rogue",
      "name": "Разбойник",
      "description": "Хитрый и быстрый. Делает ставку на скорость и внезапность.",
      "icon": "🔪",
      "startingArmy": [
        { "id": "rogue", "count": 3 }
      ]
    },
    {
      "id": "mage",
      "name": "Маг",
      "description": "Повелитель стихий. Слаб в броне, но силён в уроне.",
      "icon": "🔮",
      "startingArmy": [
        { "id": "mage", "count": 1 },
        { "id": "fireElemental", "count": 1 },
        { "id": "waterElemental", "count": 1 }
      ]
    },
    {
      "id": "ranger",
      "name": "Рейнджер",
      "description": "Мастер дальнего боя и дикой охоты.",
      "icon": "🏹",
      "startingArmy": [
        { "id": "archer", "count": 1 },
        { "id": "wolf", "count": 3 }
      ],
      "requiresAchievementId": "kill_10_wolf"
    }
  ]
}

